benchmarks/bm_2to3/run_benchmark.py
benchmarks/bm_2to3/vendor/src/lib2to3/__init__.py
benchmarks/bm_2to3/vendor/src/lib2to3/__main__.py
benchmarks/bm_2to3/vendor/src/lib2to3/btm_matcher.py
benchmarks/bm_2to3/vendor/src/lib2to3/btm_utils.py
benchmarks/bm_2to3/vendor/src/lib2to3/fixer_base.py
benchmarks/bm_2to3/vendor/src/lib2to3/fixer_util.py
benchmarks/bm_2to3/vendor/src/lib2to3/main.py
benchmarks/bm_2to3/vendor/src/lib2to3/patcomp.py
benchmarks/bm_2to3/vendor/src/lib2to3/pygram.py
benchmarks/bm_2to3/vendor/src/lib2to3/pytree.py
benchmarks/bm_2to3/vendor/src/lib2to3/refactor.py
benchmarks/bm_2to3/vendor/src/lib2to3/fixes/__init__.py
benchmarks/bm_2to3/vendor/src/lib2to3/fixes/fix_apply.py
benchmarks/bm_2to3/vendor/src/lib2to3/fixes/fix_asserts.py
benchmarks/bm_2to3/vendor/src/lib2to3/fixes/fix_basestring.py
benchmarks/bm_2to3/vendor/src/lib2to3/fixes/fix_buffer.py
benchmarks/bm_2to3/vendor/src/lib2to3/fixes/fix_dict.py
benchmarks/bm_2to3/vendor/src/lib2to3/fixes/fix_except.py
benchmarks/bm_2to3/vendor/src/lib2to3/fixes/fix_exec.py
benchmarks/bm_2to3/vendor/src/lib2to3/fixes/fix_execfile.py
benchmarks/bm_2to3/vendor/src/lib2to3/fixes/fix_exitfunc.py
benchmarks/bm_2to3/vendor/src/lib2to3/fixes/fix_filter.py
benchmarks/bm_2to3/vendor/src/lib2to3/fixes/fix_funcattrs.py
benchmarks/bm_2to3/vendor/src/lib2to3/fixes/fix_future.py
benchmarks/bm_2to3/vendor/src/lib2to3/fixes/fix_getcwdu.py
benchmarks/bm_2to3/vendor/src/lib2to3/fixes/fix_has_key.py
benchmarks/bm_2to3/vendor/src/lib2to3/fixes/fix_idioms.py
benchmarks/bm_2to3/vendor/src/lib2to3/fixes/fix_import.py
benchmarks/bm_2to3/vendor/src/lib2to3/fixes/fix_imports.py
benchmarks/bm_2to3/vendor/src/lib2to3/fixes/fix_imports2.py
benchmarks/bm_2to3/vendor/src/lib2to3/fixes/fix_input.py
benchmarks/bm_2to3/vendor/src/lib2to3/fixes/fix_intern.py
benchmarks/bm_2to3/vendor/src/lib2to3/fixes/fix_isinstance.py
benchmarks/bm_2to3/vendor/src/lib2to3/fixes/fix_itertools.py
pyperformance-1.12.0.dist-info/licenses/AUTHORS
pyperformance-1.12.0.dist-info/licenses/COPYING
pyperformance-1.12.0.dist-info/METADATA
pyperformance-1.12.0.dist-info/WHEEL
pyperformance-1.12.0.dist-info/entry_points.txt
pyperformance-1.12.0.dist-info/top_level.txt
pyperformance-1.12.0.dist-info/RECORD
