Metadata-Version: 2.4
Name: pyperformance
Version: 1.12.0
Summary: Python benchmark suite
Author: Collin Winter, Jeffrey Yasskin
License: MIT
Project-URL: Homepage, https://github.com/python/pyperformance
Classifier: Development Status :: 5 - Production/Stable
Classifier: Intended Audience :: Developers
Classifier: License :: OSI Approved :: MIT License
Classifier: Natural Language :: English
Classifier: Operating System :: OS Independent
Classifier: Programming Language :: Python
Classifier: Programming Language :: Python :: 3 :: Only
Classifier: Programming Language :: Python :: 3.10
Classifier: Programming Language :: Python :: 3.11
Classifier: Programming Language :: Python :: 3.12
Classifier: Programming Language :: Python :: 3.13
Classifier: Programming Language :: Python :: 3.14
Requires-Python: >=3.10
License-File: COPYING
License-File: AUTHORS
Requires-Dist: packaging
Requires-Dist: pyperf
Requires-Dist: tomli; python_version < "3.11"
Provides-Extra: dev
Requires-Dist: mypy==1.18.2; extra == "dev"
Requires-Dist: tomli; extra == "dev"
Requires-Dist: tox; extra == "dev"
Dynamic: license-file
